dev4py/utils/__init__.py
dev4py/utils/async_joptional.py
dev4py/utils/awaitables.py
dev4py/utils/collectors.py
dev4py/utils/dicts.py
dev4py/utils/iterables.py
dev4py/utils/joptional.py
dev4py/utils/lists.py
dev4py/utils/objects.py
dev4py/utils/pipeline/__init__.py
dev4py/utils/pipeline/simple_pipeline.py
dev4py/utils/pipeline/step_pipeline.py
dev4py/utils/retry.py
dev4py/utils/stream.py
dev4py/utils/tuples.py
dev4py/utils/types.py
dev4py_utils-4.1.0.dist-info/LICENSE
dev4py_utils-4.1.0.dist-info/METADATA
dev4py_utils-4.1.0.dist-info/WHEEL
dev4py_utils-4.1.0.dist-info/RECORD
