Metadata-Version: 2.1
Name: dev4py-utils
Version: 4.1.0
Summary: A set of Python regularly used classes/functions
Home-page: https://github.com/dev4py/dev4py-utils
License: Apache-2.0
Keywords: python,utils,function,classes
Author: St4rG00se
Author-email: st4rg00se@protonmail.com
Requires-Python: >=3.11,<4.0
Classifier: Intended Audience :: Developers
Classifier: License :: OSI Approved :: Apache Software License
Classifier: Programming Language :: Python
Classifier: Programming Language :: Python :: 3
Classifier: Programming Language :: Python :: 3.11
Classifier: Programming Language :: Python :: 3.12
Project-URL: Documentation, https://dev4py.github.io/dev4py-utils/
Project-URL: Repository, https://github.com/dev4py/dev4py-utils
